lazy_settings/__init__.py
lazy_settings/exceptions.py
lazy_settings/py.typed
lazy_settings/conf/__init__.py
lazy_settings/conf/utils.py
lazy_settings/test/__init__.py
lazy_settings/test/utils.py
lazy_settings/utils/__init__.py
lazy_settings/utils/functional.py
lazy_settings-0.1.1.dist-info/METADATA
lazy_settings-0.1.1.dist-info/WHEEL
lazy_settings-0.1.1.dist-info/licenses/LICENSE
lazy_settings-0.1.1.dist-info/RECORD
