Metadata-Version: 2.4
Name: lazy-settings
Version: 0.1.1
Summary: settings manaager for pyhton
Project-URL: Homepage, https://github.com/khiyavan/lazy-settings
Project-URL: Issues, https://github.com/khiyavan/lazy-settings/issues
Maintainer-email: amirreza <amir.rsf1380@gmail.com>
License-File: LICENSE
Classifier: Development Status :: 4 - Beta
Classifier: Environment :: Web Environment
Classifier: Intended Audience :: Developers
Classifier: Operating System :: OS Independent
Classifier: Programming Language :: Python
Classifier: Programming Language :: Python :: 3
Classifier: Programming Language :: Python :: 3 :: Only
Classifier: Programming Language :: Python :: 3.11
Classifier: Programming Language :: Python :: 3.12
Classifier: Programming Language :: Python :: 3.13
Classifier: Topic :: Software Development :: Libraries
Classifier: Topic :: Utilities
Requires-Python: >=3.11
Provides-Extra: rtoml
Requires-Dist: rtoml>=0.12.0; extra == 'rtoml'
Provides-Extra: tomli
Requires-Dist: tomli>=2.2.1; extra == 'tomli'
